ipytableview/__init__.py
ipytableview/_frontend.py
ipytableview/_version.py
ipytableview/tableview_widget.py
ipytableview/labextension/build_log.json
ipytableview/labextension/package.json
ipytableview/labextension/static/lib_index_js.019edfcf1fb7e4e0ff7a.js
ipytableview/labextension/static/lib_index_js.019edfcf1fb7e4e0ff7a.js.map
ipytableview/labextension/static/lib_plugin_js.0c0142cf4beb8ff46e1c.js
ipytableview/labextension/static/lib_plugin_js.0c0142cf4beb8ff46e1c.js.map
ipytableview/labextension/static/lib_tableview_widget_js.3d378525391ddae017a8.js
ipytableview/labextension/static/lib_tableview_widget_js.3d378525391ddae017a8.js.map
ipytableview/labextension/static/remoteEntry.96f0d2cf832f288a5522.js
ipytableview/labextension/static/remoteEntry.96f0d2cf832f288a5522.js.map
ipytableview/labextension/static/style.js
ipytableview/labextension/static/vendors-node_modules_jquery_dist_jquery_js.0ab2108f5c4807d46895.js
ipytableview/labextension/static/vendors-node_modules_jquery_dist_jquery_js.0ab2108f5c4807d46895.js.map
ipytableview/nbextension/extension.js
ipytableview/nbextension/index.js
ipytableview/nbextension/index.js.LICENSE.txt
ipytableview/nbextension/index.js.map
ipytableview/tests/__init__.py
ipytableview/tests/conftest.py
ipytableview/tests/test_nbextension_path.py
ipytableview/tests/test_tableview.py
ipytableview-0.1.5.data/data/etc/jupyter/nbconfig/notebook.d/ipytableview.json
ipytableview-0.1.5.data/data/share/jupyter/labextensions/ipytableview/build_log.json
ipytableview-0.1.5.data/data/share/jupyter/labextensions/ipytableview/install.json
ipytableview-0.1.5.data/data/share/jupyter/labextensions/ipytableview/package.json
ipytableview-0.1.5.data/data/share/jupyter/labextensions/ipytableview/static/lib_index_js.019edfcf1fb7e4e0ff7a.js
ipytableview-0.1.5.data/data/share/jupyter/labextensions/ipytableview/static/lib_index_js.019edfcf1fb7e4e0ff7a.js.map
ipytableview-0.1.5.dist-info/LICENSE.txt
ipytableview-0.1.5.dist-info/METADATA
ipytableview-0.1.5.dist-info/WHEEL
ipytableview-0.1.5.dist-info/top_level.txt
ipytableview-0.1.5.dist-info/RECORD
